{ "margin":0,
 "name":"FUmaterials",
 "properties":
    {},
 "spacing":0,
 "tilecount":11,
 "tileheight":8,
 "tiles":
    {
     "0":
        {
         "image":"..\/..\/..\/..\/..\/tiled\/frackinuniverse-custom\/materials\/elderblock1.png"
        },
     "1":
        {
         "image":"..\/..\/..\/..\/..\/tiled\/frackinuniverse-custom\/materials\/elderblock2.png"
        },
     "10":
        {
         "image":"..\/..\/..\/..\/..\/tiled\/frackinuniverse-custom\/materials\/protorock.png"
        },
     "2":
        {
         "image":"..\/..\/..\/..\/..\/tiled\/frackinuniverse-custom\/materials\/elderplatform.png"
        },
     "3":
        {
         "image":"..\/..\/..\/..\/..\/tiled\/frackinuniverse-custom\/materials\/elderstone.png"
        },
     "4":
        {
         "image":"..\/..\/..\/..\/..\/tiled\/frackinuniverse-custom\/materials\/elderstone2.png"
        },
     "5":
        {
         "image":"..\/..\/..\/..\/..\/tiled\/frackinuniverse-custom\/materials\/eldertile.png"
        },
     "6":
        {
         "image":"..\/..\/..\/..\/..\/tiled\/frackinuniverse-custom\/materials\/iceblock1.png"
        },
     "7":
        {
         "image":"..\/..\/..\/..\/..\/tiled\/frackinuniverse-custom\/materials\/iceblock2.png"
        },
     "8":
        {
         "image":"..\/..\/..\/..\/..\/tiled\/frackinuniverse-custom\/materials\/iceblock3.png"
        },
     "9":
        {
         "image":"..\/..\/..\/..\/..\/tiled\/frackinuniverse-custom\/materials\/iceblock4.png"
        }
    },
 "tilewidth":8
}